[
  { "id": 1, "tedim": "Piancilna", "svenska": "Första Moseboken" },
  { "id": 2, "tedim": "Paikhiatna", "svenska": "Andra Moseboken" },
  { "id": 3, "tedim": "Siampi Laibu", "svenska": "Tredje Moseboken" },
  { "id": 4, "tedim": "Gamlak-vakna", "svenska": "Fjärde Moseboken" },
  { "id": 5, "tedim": "Thu-hilhkikna", "svenska": "Femte Moseboken" },
  { "id": 6, "tedim": "Joshua", "svenska": "Josua" },
  { "id": 7, "tedim": "Thukhente", "svenska": "Domarboken" },
  { "id": 8, "tedim": "Ruth", "svenska": "Rut" },
  { "id": 9, "tedim": "Samuel Masa", "svenska": "Första Samuelsboken" },
  { "id": 10, "tedim": "Samuel Nihna", "svenska": "Andra Samuelsboken" },
  { "id": 11, "tedim": "Kumpite Masa", "svenska": "Första Kungaboken" },
  { "id": 12, "tedim": "Kumpite Nihna", "svenska": "Andra Kungaboken" },
  { "id": 13, "tedim": "Khang-tangthu Masa", "svenska": "Första Krönikeboken" },
  { "id": 14, "tedim": "Khang-tangthu Nihna", "svenska": "Andra Krönikeboken" },
  { "id": 15, "tedim": "Ezra", "svenska": "Esra" },
  { "id": 16, "tedim": "Nehemiah", "svenska": "Nehemja" },
  { "id": 17, "tedim": "Esther", "svenska": "Ester" },
  { "id": 18, "tedim": "Job", "svenska": "Job" },
  { "id": 19, "tedim": "Late", "svenska": "Psaltaren" },
  { "id": 20, "tedim": "Paunak", "svenska": "Ordspråksboken" },
  { "id": 21, "tedim": "Thuhilh-sia", "svenska": "Predikaren" },
  { "id": 22, "tedim": "Solomon la", "svenska": "Höga Visan" },
  { "id": 23, "tedim": "Isaiah", "svenska": "Jesaja" },
  { "id": 24, "tedim": "Jeremiah", "svenska": "Jeremia" },
  { "id": 25, "tedim": "Kah la", "svenska": "Klagovisorna" },
  { "id": 26, "tedim": "Ezekiel", "svenska": "Hesekiel" },
  { "id": 27, "tedim": "Daniel", "svenska": "Daniel" },
  { "id": 28, "tedim": "Hosea", "svenska": "Hosea" },
  { "id": 29, "tedim": "Joel", "svenska": "Joel" },
  { "id": 30, "tedim": "Amos", "svenska": "Amos" },
  { "id": 31, "tedim": "Obadiah", "svenska": "Obadja" },
  { "id": 32, "tedim": "Jonah", "svenska": "Jona" },
  { "id": 33, "tedim": "Micah", "svenska": "Mika" },
  { "id": 34, "tedim": "Nahum", "svenska": "Nahum" },
  { "id": 35, "tedim": "Habakkuk", "svenska": "Habackuk" },
  { "id": 36, "tedim": "Zefaniah", "svenska": "Sefanja" },
  { "id": 37, "tedim": "Haggai", "svenska": "Haggai" },
  { "id": 38, "tedim": "Zekhariah", "svenska": "Sakarja" },
  { "id": 39, "tedim": "Malakhi", "svenska": "Malaki" },
  { "id": 40, "tedim": "Mattiu", "svenska": "Matteusevangeliet" },
  { "id": 41, "tedim": "Marka", "svenska": "Markusevangeliet" },
  { "id": 42, "tedim": "Luka", "svenska": "Lukasevangeliet" },
  { "id": 43, "tedim": "Johan", "svenska": "Johannesevangeliet" },
  { "id": 44, "tedim": "Sawltak", "svenska": "Apostlagärningarna" },
  { "id": 45, "tedim": "Rom", "svenska": "Romarbrevet" },
  { "id": 46, "tedim": "Korin Masa", "svenska": "Första Korinthierbrevet" },
  { "id": 47, "tedim": "Korin Nihna", "svenska": "Andra Korinthierbrevet" },
  { "id": 48, "tedim": "Galati", "svenska": "Galaterbrevet" },
  { "id": 49, "tedim": "Efesa", "svenska": "Efesierbrevet" },
  { "id": 50, "tedim": "Filippi", "svenska": "Filipperbrevet" },
  { "id": 51, "tedim": "Kolose", "svenska": "Kolosserbrevet" },
  { "id": 52, "tedim": "Thesalon Masa", "svenska": "Första Thessalonikerbrevet" },
  { "id": 53, "tedim": "Thesalon Nihna", "svenska": "Andra Thessalonikerbrevet" },
  { "id": 54, "tedim": "Timoti Masa", "svenska": "Första Timotheosbrevet" },
  { "id": 55, "tedim": "Timoti Nihna", "svenska": "Andra Timotheosbrevet" },
  { "id": 56, "tedim": "Titu", "svenska": "Titusbrevet" },
  { "id": 57, "tedim": "Filemon", "svenska": "Filemonbrevet" },
  { "id": 58, "tedim": "Hebru", "svenska": "Hebreerbrevet" },
  { "id": 59, "tedim": "Jeim", "svenska": "Jakobsbrevet" },
  { "id": 60, "tedim": "Piter Masa", "svenska": "Första Petrusbrevet" },
  { "id": 61, "tedim": "Piter Nihna", "svenska": "Andra Petrusbrevet" },
  { "id": 62, "tedim": "Johan Masa", "svenska": "Första Johannesbrevet" },
  { "id": 63, "tedim": "Johan Nihna", "svenska": "Andra Johannesbrevet" },
  { "id": 64, "tedim": "Johan Thumna", "svenska": "Tredje Johannesbrevet" },
  { "id": 65, "tedim": "Juda", "svenska": "Judasbrevet" },
  { "id": 66, "tedim": "Mangmuhna", "svenska": "Uppenbarelseboken" }
]